src/__init__.py
src/trade_helper_0xhexe/__init__.py
src/trade_helper_0xhexe/providers/__init__.py
src/trade_helper_0xhexe/providers/provider.py
src/trade_helper_0xhexe/providers/upstox.py
src/trade_helper_0xhexe/tickers/__init__.py
src/trade_helper_0xhexe/tickers/bollinger_bands.py
src/trade_helper_0xhexe/tickers/heikin_ashi.py
src/trade_helper_0xhexe/tickers/strategy_ticker.py
src/trade_helper_0xhexe/type/__init__.py
src/trade_helper_0xhexe/type/tick_data.py
tests/__init__.py
tests/test_ha.py
tests/test_providers.py
tests/test_tickers.py
trade_helpers-1.0.0.dist-info/LICENSE
trade_helpers-1.0.0.dist-info/METADATA
trade_helpers-1.0.0.dist-info/WHEEL
trade_helpers-1.0.0.dist-info/top_level.txt
trade_helpers-1.0.0.dist-info/RECORD
