Metadata-Version: 2.1
Name: trade_helpers
Version: 1.0.0
Summary: A collection of helper functions for trading
Author: Omkar Yadav<me@f22.dev>
Author-email: Omkar Yadav <me@f22.dev>
License: Apache License
Project-URL: Homepage, https://github.com/0xHexE/trade-helpers
Classifier: License :: OSI Approved :: Apache Software License
Classifier: Programming Language :: Python
Classifier: Programming Language :: Python :: 3
Requires-Python: >=3.12
License-File: LICENSE
Requires-Dist: numpy
Requires-Dist: requests
Provides-Extra: dev
Requires-Dist: black ; extra == 'dev'
Requires-Dist: bumpver ; extra == 'dev'
Requires-Dist: isort ; extra == 'dev'
Requires-Dist: pip-tools ; extra == 'dev'
Requires-Dist: pytest ; extra == 'dev'
